pyats/connections/__init__.py
pyats/connections/bases.cpython-313-aarch64-linux-gnu.so
pyats/connections/hooks.cpython-313-aarch64-linux-gnu.so
pyats/connections/manager.cpython-313-aarch64-linux-gnu.so
pyats/connections/pool.cpython-313-aarch64-linux-gnu.so
pyats/connections/utils.cpython-313-aarch64-linux-gnu.so
pyats/connections/wrapper.cpython-313-aarch64-linux-gnu.so
pyats_connections-25.9.dist-info/METADATA
pyats_connections-25.9.dist-info/WHEEL
pyats_connections-25.9.dist-info/top_level.txt
pyats_connections-25.9.dist-info/RECORD
